{
  "url": "http://www.sollentunahockey.com/",
  "title": "http://www.sollentunahockey.com/",
  "content": "# http://www.sollentunahockey.com/\n\nSollentuna Hockey \u00e4r stolta \u00f6ver att meddela att det svenska cybers\u00e4kerhetsf\u00f6retaget Cyloq AB blir ny arenasponsor f\u00f6r Sollentuna HCs hemmaarenor. Det inneb\u00e4r att ishallarna nu kommer att b\u00e4ra namnen Cyloq Arena och Cyloq Annex, vilket markerar en gemensam satsning p\u00e5 lokal utveckling, idrott och digital trygghet.\n\nSollentuna Hockey \u00e4r en hockeyklubb bel\u00e4gen i Sollentuna, Sverige. Klubben \u00e4r aktiv inom ungdoms- och seniorhockey och erbjuder olika tr\u00e4nings- och t\u00e4vlingsm\u00f6jligheter f\u00f6r spelare i alla \u00e5ldrar.\n\n## Nyheter\n\n### CYLOQ ny arenasponsor (2025-05-27)\n\nCYLOQ blir Sollentuna Hockeys nya arenasponsor. L\u00e4s mer [h\u00e4r](https://sollentunahockey.myclub.se/site_node/254/nyheter/cyloq-ny-arenasponsor).\n\n### Kallelse till \u00e5rsm\u00f6te (2025-05-27)\n\nDen 17 juni kommer Sollentuna Hockey h\u00e5lla ordinarie \u00e5rsm\u00f6te. L\u00e4s mer [h\u00e4r](https://sollentunahockey.myclub.se/site_node/254/nyheter/kallelse-till-arsmote).\n\n### Info fr\u00e5n Valberedningen (2025-05-09)\n\nVi i valberedningen forts\u00e4tter v\u00e5rt arbete inf\u00f6r \u00e5rsm\u00f6tet i juni och vill fortsatt ha era synpunkter och tankar g\u00e4llande ledam\u00f6ter till Sollentuna Hockeys styrelse. L\u00e4s mer [h\u00e4r](https://sollentunahockey.myclub.se/site_node/254/nyheter/info-fran-valberedningen-845b199b-3203-4a92-a2a9-6bd06052db0c).\n\n### Try Out Weekend J18 - 26-27 april (2025-04-20)\n\nDen 26-27 april h\u00e5ller vi Try Out inf\u00f6r s\u00e4songen 2025/2026. L\u00e4s mer [h\u00e4r](https://sollentunahockey.myclub.se/site_node/254/nyheter/try-out-j18-weekend-26-27-april).\n\n### Ny skillstr\u00e4nare och huvudtr\u00e4nare f\u00f6r n\u00e4sta \u00e5rs U15 \u00e4r klar. (2025-04-19)\n\nL\u00e4s mer [h\u00e4r](https://sollentunahockey.myclub.se/site_node/254/nyheter/ny-skillstranare-och-huvudtranare-for-nasta-ars-u15-ar-klar).\n\n### SHC J18 Try Out weekend 26-27 April (2025-04-17)\n\n26-27 April h\u00e5ller vi Try Out inf\u00f6r s\u00e4songen 25/26. L\u00e4s mer [h\u00e4r](https://sollentunahockey.myclub.se/site_node/1263/nyheter/shc-j18-try-out-weekend-26-27-april).\n\n### V\u00e4lkommen Head Coach - Nichlas Falk (2025-03-21)\n\nNichlas kliver p\u00e5 31 mars \u2764\ufe0f\ud83e\udd0d\ud83d\udc99. L\u00e4s mer [h\u00e4r](https://sollentunahockey.myclub.se/site_node/7699/nyheter/nichlas-falk-blir-head-coach-for-team-10).\n\n### RE:FI STHLM - Tack f\u00f6r ert st\u00f6d! (2024-12-18)\n\nRE:FI STHLM is a Stockholm-based law firm specialising in transactional finance law. L\u00e4s mer [h\u00e4r](https://sollentunahockey.myclub.se/site_node/9038/nyheter/refi-sthlm-tack-for-ert-stod).\n\n### Tryout 17 december (2024-12-09)\n\nDen 17 december h\u00e5ller vi Tryout 2. L\u00e4s mer [h\u00e4r](https://sollentunahockey.myclub.se/site_node/1263/nyheter/tryout-17-december).\n\n### J18 forts\u00e4tter att spela bra (2024-11-11)\n\nTre raka segrar sedan h\u00f6stlovet. L\u00e4s mer [h\u00e4r](https://sollentunahockey.myclub.se/site_node/1263/nyheter/j18-lag-fortsatter-spela-bra).\n\n## Kontakt\n\nF\u00f6r mer information, kontakta kansliet via mejl: kansli@sollentunahockey.com eller telefon: 0709\u201316 05 73 (mellan 10\u201314).",
  "html": "",
  "extracted_news": [
    {
      "date": "2025-05-09",
      "title": "Info fr\u00e5n Valberedningen",
      "content": "Vi i valberedningen forts\u00e4tter v\u00e5rt arbete inf\u00f6r \u00e5rsm\u00f6tet i juni och vill fortsatt ha era synpunkter och tankar g\u00e4llande ledam\u00f6ter till Sollentuna Hockeys styrelse.",
      "first_seen": "2025-05-22T21:22:05.923165",
      "url": "http://www.sollentunahockey.com/"
    },
    {
      "date": "2025-04-20",
      "title": "Try Out Weekend J18 - 26-27 april",
      "content": "Den 26-27 april h\u00e5ller vi Try Out inf\u00f6r s\u00e4songen 2025/2026.",
      "first_seen": "2025-05-22T21:22:05.923178",
      "url": "http://www.sollentunahockey.com/"
    },
    {
      "date": "2025-04-19",
      "title": "Ny skillstr\u00e4nare och huvudtr\u00e4nare f\u00f6r n\u00e4sta \u00e5rs U15 \u00e4r klar.",
      "content": "",
      "first_seen": "2025-05-22T21:22:05.923180",
      "url": "http://www.sollentunahockey.com/"
    },
    {
      "date": "2025-03-17",
      "title": "Efters\u00e4songsprogrammet uppdaterade grupper",
      "content": "",
      "first_seen": "2025-05-22T21:22:05.923181",
      "url": "http://www.sollentunahockey.com/"
    },
    {
      "date": "2025-03-17",
      "title": "Valberedningen informerar",
      "content": "P\u00e5b\u00f6rjat arbete inf\u00f6r \u00e5rsm\u00f6tet i juni.",
      "first_seen": "2025-05-22T21:22:05.923182",
      "url": "http://www.sollentunahockey.com/"
    },
    {
      "date": "2025-04-17",
      "title": "SHC J18 Try Out weekend 26-27 April",
      "content": "26-27 April h\u00e5ller vi Try Out inf\u00f6r s\u00e4songen 25/26.",
      "first_seen": "2025-05-22T21:22:05.923183",
      "url": "http://www.sollentunahockey.com/"
    },
    {
      "date": "2025-03-21",
      "title": "V\u00e4lkommen Head Coach - Nichlas Falk",
      "content": "Nichlas kliver p\u00e5 31 mars \u2764\ufe0f\ud83e\udd0d\ud83d\udc99.",
      "first_seen": "2025-05-22T21:22:05.923184",
      "url": "http://www.sollentunahockey.com/"
    },
    {
      "date": "2024-12-18",
      "title": "RE:FI STHLM - Tack f\u00f6r ert st\u00f6d!",
      "content": "RE:FI STHLM is a Stockholm-based law firm specialising in transactional finance law. Our firm is distinguished by a standout team with over two decades of experience providing legal advice to lenders and borrowers on high-end financing mandates and debt restructurings.",
      "first_seen": "2025-05-22T21:22:05.923185",
      "url": "http://www.sollentunahockey.com/"
    },
    {
      "date": "2024-12-09",
      "title": "Tryout 17 december",
      "content": "Den 17 december h\u00e5ller vi Tryout 2.",
      "first_seen": "2025-05-22T21:22:05.923186",
      "url": "http://www.sollentunahockey.com/"
    },
    {
      "date": "2024-11-11",
      "title": "J18 forts\u00e4tter att spela bra",
      "content": "Tre raka segrar sedan h\u00f6stlovet.",
      "first_seen": "2025-05-22T21:22:05.923187",
      "url": "http://www.sollentunahockey.com/"
    },
    {
      "date": "2025-05-27",
      "title": "CYLOQ ny arenasponsor",
      "content": "CYLOQ blir Sollentuna Hockeys nya arenasponsor. L\u00e4s mer [h\u00e4r](https://sollentunahockey.myclub.se/site_node/254/nyheter/cyloq-ny-arenasponsor).",
      "first_seen": "2025-05-27T23:58:32.841876",
      "url": "http://www.sollentunahockey.com/"
    },
    {
      "date": "2025-05-27",
      "title": "Kallelse till \u00e5rsm\u00f6te",
      "content": "Den 17 juni kommer Sollentuna Hockey h\u00e5lla ordinarie \u00e5rsm\u00f6te. L\u00e4s mer [h\u00e4r](https://sollentunahockey.myclub.se/site_node/254/nyheter/kallelse-till-arsmote).",
      "first_seen": "2025-05-27T23:58:32.841878",
      "url": "http://www.sollentunahockey.com/"
    }
  ],
  "general_info": {
    "body": "Sollentuna Hockey \u00e4r en hockeyklubb bel\u00e4gen i Sollentuna, Sverige. Klubben \u00e4r aktiv inom ungdoms- och seniorhockey och erbjuder olika tr\u00e4nings- och t\u00e4vlingsm\u00f6jligheter f\u00f6r spelare i alla \u00e5ldrar.",
    "description": "Sollentuna Hockey \u00e4r stolta \u00f6ver att meddela att det svenska cybers\u00e4kerhetsf\u00f6retaget Cyloq AB blir ny arenasponsor f\u00f6r Sollentuna HCs hemmaarenor. Det inneb\u00e4r att ishallarna nu kommer att b\u00e4ra namnen Cyloq Arena och Cyloq Annex, vilket markerar en gemensam satsning p\u00e5 lokal utveckling, idrott och digital trygghet.",
    "contact_info": "F\u00f6r mer information, kontakta kansliet via mejl: kansli@sollentunahockey.com eller telefon: 0709\u201316 05 73 (mellan 10\u201314)."
  },
  "timestamp": "2025-05-28T19:20:30.178775",
  "stored_at": "2025-05-28T19:20:53.350664"
}