{
  "url": "https://www.sollentunasodra.se/",
  "title": "https://www.sollentunasodra.se/",
  "content": "# https://www.sollentunasodra.se/\n\nVi \u00e4r raised by adventure. Det b\u00e4sta vi vet \u00e4r \u00e4ventyr, vilket formar oss till dem vi \u00e4r och kan bli.\n\nSollentuna S\u00f6dra Scoutk\u00e5r \u00e4r en land- och sj\u00f6scoutk\u00e5r i Sollentuna som erbjuder scouting f\u00f6r alla \u00e5ldrar, fr\u00e5n 7 till 25 \u00e5r. K\u00e5ren fokuserar p\u00e5 \u00e4ventyr och gemenskap.\n\n## Nyheter\n\n### Terminsavslutning (2025-05-28)\n\nVi tackar f\u00f6r i \u00e5r med att samla k\u00e5ren den 2 juni 18:30-20:00 vid Holken!\n\n### Ugglan Hoar i Maj 2025 (2025-05-23)\n\nSlutdatum f\u00f6r ledar/funktion\u00e4rs-enk\u00e4ten s\u00f6ndag 1 juni. Terminsavslutning m\u00e5ndagen den 2 juni. Dags f\u00f6r scouterna att \u00f6nska dag inf\u00f6r h\u00f6sten. P\u00e5minnelse om Sensus-listor. Inf\u00f6r hajken \u2013 det finns korv & br\u00f6d i frysen i garaget.\n\n### Ugglan Hoar i April 2025 (2025-04-29)\n\nF\u00f6rskolans saker \u2013 inomhus och utomhus. KLUR-hajk 10-11 maj. KLUR-kv\u00e4ll \u2013 s\u00f6ndag 18 maj. Bokning av hajkutrustning. Scoutsigill-st\u00e4mplar. Sommarl\u00e4ger.\n\n### V\u00e4lkommen p\u00e5 Sommarl\u00e4ger 2025! (2025-04-15)\n\nDet ryktas att de tre br\u00f6derna Trassel st\u00e4ller till trubbel i de vilda trakterna v\u00e4ster om Hudiksvall. Sheriff Tom Horn beh\u00f6ver er hj\u00e4lp. F\u00f6lj med p\u00e5 l\u00e4gret i sommar och hj\u00e4lp honom att f\u00e5 ordning i staden! Nu har anm\u00e4lan till \u00e5rets roligaste h\u00e4ndelse \u2013 sommarl\u00e4gret \u2013 \u00f6ppnat.\n\n### Informationsm\u00f6te f\u00f6r blivande B\u00e4verledare (2025-03-13)\n\nM\u00e5ndag 7 april eller onsdag 9 april kl 19.00 v\u00e4lkomnas blivande B\u00e4verledare p\u00e5 ett informationsm\u00f6te inf\u00f6r h\u00f6stterminen 2025.\n\n### Ugglan Hoar i Mars 2025 (2025-03-08)\n\nF\u00f6rskolans saker \u2013 inomhus och utomhus. KLUR-hajk 10-11 maj. KLUR-kv\u00e4ll \u2013 s\u00f6ndag 18 maj. Bokning av hajkutrustning. Scoutsigill-st\u00e4mplar. Sommarl\u00e4ger.\n\n### Ugglan Hoar i Februari 2025 (2025-02-13)\n\nExtra k\u00e5rst\u00e4mma onsdagen den 19 mars kl 18.30. KLUR-aktivitet s\u00f6ndagen den 18 maj. Sommarl\u00e4gret s\u00f6ker funktion\u00e4rer \u2013 framf\u00f6rallt till funk-k\u00f6ket.\n\n### Vi lanserar appen LedarABC! (2025-02-13)\n\nApp lanserad: LedarABC \u2013 Din digitala verktygsl\u00e5da i Sollentuna S\u00f6dra.\n\n### Ugglan Hoar i Januari 2025 (2025-01-08)\n\nNy larmkod och nytt l\u00f6senord till Holken. Krisplanen. Bl\u00e5b\u00e4rskurs. H\u00e4lsning fr\u00e5n Materielgruppen.\n\n### Ugglan Hoar i December 2024 (2024-12-08)\n\nJulgransf\u00f6rs\u00e4ljning \u2013 och k\u00f6rning av granar! Seglarskoleledare s\u00f6kes till sommaren 2025.\n\n### Ugglan Hoar i November 2024 (2024-11-08)\n\nJulavslutning onsdag 4 december kl 18.30. Sensus-stuga \u2013 ledarh\u00e4ng i Holken efter avslutningen.\n\n### Ugglan Hoar efter K\u00e5rst\u00e4mman (2024-11-06)\n\nHej alla KLURiga! \u00c5rets k\u00e5rst\u00e4mma \u00e4r avklarad, Tack Albin som lotsade oss igenom dagordningens alla punkter.\n\n### Ugglan Hoar i Oktober 2024 (2024-10-20)\n\n\u2022 Arbetsdag i Holken 10 november. \u2022 Dags att s\u00f6ka k\u00e5rens utmanarstipendier.\n\n### Ugglan Hoar \u2013 september 2024 (2024-10-09)\n\nHej alla KLURiga! H\u00f6stterminen \u00e4r i full g\u00e5ng, och nu har \u00e4ven v\u00e5ra nya b\u00e4vrar tr\u00e4ffats p\u00e5 sitt f\u00f6rsta m\u00f6te.\n\n## Kontakt\n\nF\u00f6r mer information, bes\u00f6k v\u00e5r hemsida p\u00e5 https://sollentunasodra.se/ eller kontakta oss via v\u00e5r kontaktsektion.",
  "html": "",
  "extracted_news": [
    {
      "date": "2025-04-29",
      "title": "Ugglan Hoar i April 2025",
      "content": "F\u00f6rskolans saker \u2013 inomhus och utomhus\n\nKLUR-hajk 10-11 maj\n\nKLUR-kv\u00e4ll \u2013 s\u00f6ndag 18 maj\n\nBokning av hajkutrustning\n\nScoutsigill-st\u00e4mplar\n\nSommarl\u00e4ger\n\nLedarplanering inf\u00f6r h\u00f6stterminen\n\nPsykisk livr\u00e4ddning f\u00f6r scoutledare\n\n[L\u00e4s mer](https://sollentunasodra.se/ugglan-hoar-i-april-2025/)",
      "first_seen": "2025-05-22T15:43:25.760002",
      "url": "https://www.sollentunasodra.se/"
    },
    {
      "date": "2025-05-23",
      "title": "Ugglan Hoar i Maj 2025",
      "content": "Slutdatum f\u00f6r ledar/funktion\u00e4rs-enk\u00e4ten s\u00f6ndag 1 juni\nTerminsavslutning m\u00e5ndagen den 2 juni\nDags f\u00f6r scouterna att \u00f6nska dag inf\u00f6r h\u00f6sten\nP\u00e5minnelse om Sensus-listor\nInf\u00f6r hajken \u2013 det finns korv & br\u00f6d i frysen i garaget\nAvdelningskylen i garaget\nWhatsApp-grupp f\u00f6r KLUR\nMeddelande fr\u00e5n Birka scoutdistrikts Valberedning\n[L\u00e4s mer](https://sollentunasodra.se/ugglan-hoar-i-maj-2025/)",
      "first_seen": "2025-05-27T23:42:04.521194",
      "url": "https://www.sollentunasodra.se/"
    },
    {
      "date": "2025-04-15",
      "title": "V\u00e4lkommen p\u00e5 Sommarl\u00e4ger 2025!",
      "content": "Det ryktas att de tre br\u00f6derna Trassel st\u00e4ller till trubbel i de vilda trakterna v\u00e4ster om Hudiksvall. Sheriff Tom Horn beh\u00f6ver er hj\u00e4lp. F\u00f6lj med p\u00e5 l\u00e4gret i sommar och hj\u00e4lp honom att f\u00e5 ordning i staden! Nu har anm\u00e4lan till \u00e5rets roligaste h\u00e4ndelse \u2013 sommarl\u00e4gret \u2013 \u00f6ppnat. Anm\u00e4lan sker via Scoutnet.",
      "first_seen": "2025-05-28T09:23:16.926978",
      "url": "https://www.sollentunasodra.se/"
    },
    {
      "date": "2025-03-13",
      "title": "Informationsm\u00f6te f\u00f6r blivande B\u00e4verledare",
      "content": "M\u00e5ndag 7 april eller onsdag 9 april kl 19.00 v\u00e4lkomnas blivande B\u00e4verledare p\u00e5 ett informationsm\u00f6te inf\u00f6r h\u00f6stterminen 2025.",
      "first_seen": "2025-05-28T09:23:16.926979",
      "url": "https://www.sollentunasodra.se/"
    },
    {
      "date": "2025-03-08",
      "title": "Ugglan Hoar i Mars 2025",
      "content": "F\u00f6rskolans saker \u2013 inomhus och utomhus\nKLUR-hajk 10-11 maj\nKLUR-kv\u00e4ll \u2013 s\u00f6ndag 18 maj\nBokning av hajkutrustning\nScoutsigill-st\u00e4mplar\nSommarl\u00e4ger\nLedarplanering inf\u00f6r h\u00f6stterminen\nPsykisk livr\u00e4ddning f\u00f6r scoutledare.",
      "first_seen": "2025-05-28T09:23:16.926980",
      "url": "https://www.sollentunasodra.se/"
    },
    {
      "date": "2025-02-13",
      "title": "Ugglan Hoar i Februari 2025",
      "content": "Extra k\u00e5rst\u00e4mma onsdagen den 19 mars kl 18.30\nKLUR-aktivitet s\u00f6ndagen den 18 maj\nSommarl\u00e4gret s\u00f6ker funktion\u00e4rer \u2013 framf\u00f6rallt till funk-k\u00f6ket.",
      "first_seen": "2025-05-28T09:23:16.926981",
      "url": "https://www.sollentunasodra.se/"
    },
    {
      "date": "2025-02-13",
      "title": "Vi lanserar appen LedarABC!",
      "content": "App lanserad: LedarABC \u2013 Din digitala verktygsl\u00e5da i Sollentuna S\u00f6dra.",
      "first_seen": "2025-05-28T09:23:16.926982",
      "url": "https://www.sollentunasodra.se/"
    },
    {
      "date": "2025-01-08",
      "title": "Ugglan Hoar i Januari 2025",
      "content": "Ny larmkod och nytt l\u00f6senord till Holken\nKrisplanen\nBl\u00e5b\u00e4rskurs\nH\u00e4lsning fr\u00e5n Materielgruppen\nV\u00e4djan fr\u00e5n v\u00e5r st\u00e4dfirma\nInbjudan SSKS vuxenkurs i jollesegling.",
      "first_seen": "2025-05-28T09:23:16.926983",
      "url": "https://www.sollentunasodra.se/"
    },
    {
      "date": "2024-12-08",
      "title": "Ugglan Hoar i December 2024",
      "content": "Julgransf\u00f6rs\u00e4ljning \u2013 och k\u00f6rning av granar!\nSeglarskoleledare s\u00f6kes till sommaren 2025\nKompassenvecka\nMidvinterblot\nRiksskeppsr\u00e5d\nV\u00e5rens \u2013 prelimin\u00e4ra \u2013 terminsprogram\nVargarnas \u00c4ventyrskurs.",
      "first_seen": "2025-05-28T09:23:16.926984",
      "url": "https://www.sollentunasodra.se/"
    },
    {
      "date": "2024-11-08",
      "title": "Ugglan Hoar i November 2024",
      "content": "Julavslutning onsdag 4 december kl 18.30\nSensus-stuga \u2013 ledarh\u00e4ng i Holken efter avslutningen\nF\u00f6rs\u00e4ljning av Scouternas julprodukter\nGr\u00f6tfest f\u00f6r KLUR m\u00e5ndag 9 december kl 18.30\nMidvinterblot \u2013 v\u00e5rens uppstartshelg f\u00f6r ledare 10-12 januari 2025\nJulgransf\u00f6rs\u00e4ljning\nSn\u00f6skottning vid Holken\nSeglarskoleledare s\u00f6kes till sommaren 2025.",
      "first_seen": "2025-05-28T09:23:16.926985",
      "url": "https://www.sollentunasodra.se/"
    },
    {
      "date": "2024-11-06",
      "title": "Ugglan Hoar efter K\u00e5rst\u00e4mman",
      "content": "Hej alla KLURiga! \u00c5rets k\u00e5rst\u00e4mma \u00e4r avklarad, Tack Albin som lotsade oss igenom dagordningens alla punkter, och Malin som pr\u00e4ntade ner alla beslut! Vi passar p\u00e5 och tackar Malin, Joel, Iris och Joanna som slutar i k\u00e5rstyrelsen efter ett eller flera \u00e5rs insats! Och Tack Valberedningen som ringt och ringt och pratat och pratat.",
      "first_seen": "2025-05-28T09:23:16.926986",
      "url": "https://www.sollentunasodra.se/"
    },
    {
      "date": "2024-10-20",
      "title": "Ugglan Hoar i Oktober 2024",
      "content": "\u2022 Arbetsdag i Holken 10 november\n\u2022 Dags att s\u00f6ka k\u00e5rens utmanarstipendier\n\u2022 K\u00e5rens Krisplan\n\u2022 Kompassenm\u00f6ten f\u00f6r k\u00e5rens arbetsgrupper\n\u2022 Teambuilding f\u00f6r k\u00e5rens ledarteam\n\u2022 Belysning till grusplanen vid eldst\u00e4derna\n\u2022 P\u00e5minnelse om att sl\u00e4cka lampor och l\u00e5sa d\u00f6rrar & f\u00f6nster\n\u2022 Midvinterblot \u2013 v\u00e5rterminens planeringshelg. Save the date!",
      "first_seen": "2025-05-28T09:23:16.926986",
      "url": "https://www.sollentunasodra.se/"
    },
    {
      "date": "2024-10-09",
      "title": "Ugglan Hoar \u2013 september 2024",
      "content": "Hej alla KLURiga! H\u00f6stterminen \u00e4r i full g\u00e5ng, och nu har \u00e4ven v\u00e5ra nya b\u00e4vrar tr\u00e4ffats p\u00e5 sitt f\u00f6rsta m\u00f6te. Det kryllar av scouter och ledare utanf\u00f6r Holken p\u00e5 kv\u00e4llarna, och vid Skutan vimlar det av segel. h\u00e4rligt att vara ig\u00e5ng igen.",
      "first_seen": "2025-05-28T09:23:16.926987",
      "url": "https://www.sollentunasodra.se/"
    },
    {
      "date": "2025-05-28",
      "title": "Terminsavslutning",
      "content": "Vi tackar f\u00f6r i \u00e5r med att samla k\u00e5ren den 2 juni 18:30-20:00 vid Holken!",
      "first_seen": "2025-05-28T14:10:09.392671",
      "url": "https://www.sollentunasodra.se/"
    }
  ],
  "general_info": {
    "body": "Sollentuna S\u00f6dra Scoutk\u00e5r \u00e4r en land- och sj\u00f6scoutk\u00e5r i Sollentuna som erbjuder scouting f\u00f6r alla \u00e5ldrar, fr\u00e5n 7 till 25 \u00e5r. K\u00e5ren fokuserar p\u00e5 \u00e4ventyr och gemenskap.",
    "description": "Vi \u00e4r raised by adventure. Det b\u00e4sta vi vet \u00e4r \u00e4ventyr, vilket formar oss till dem vi \u00e4r och kan bli.",
    "contact_info": "F\u00f6r mer information, bes\u00f6k v\u00e5r hemsida p\u00e5 https://sollentunasodra.se/ eller kontakta oss via v\u00e5r kontaktsektion."
  },
  "timestamp": "2025-05-28T19:27:48.751798",
  "stored_at": "2025-05-28T19:27:48.757792"
}