{
  "url": "https://www.sollentunafk.se/aktuellt/",
  "title": "https://www.sollentunafk.se/aktuellt/",
  "content": "# https://www.sollentunafk.se/aktuellt/\n\nAktuellt \u2013 Sollentuna FK\n\nEttanfotboll.se drivs av f\u00f6reningen Ettanfotboll. F\u00f6reningen Ettanfotboll \u00e4r en intresseorganisation f\u00f6r de 32 klubbarna i Ettan. Uppdraget \u00e4r att driva utvecklingen av den semiprofessionella fotbollen; sportsligt, ekonomiskt, kommersiellt och administrativt.\n\n## Nyheter\n\n### Matchrapport: Heffnersklubban-SFK Dam (2025-05-28)\n\nL\u00e4s mer\n\n### Matchrapport: SFK Herr-Karlstad (2025-05-28)\n\nL\u00e4s mer\n\n### Matchrapport: SFK Dam-T\u00e4by (2025-05-20)\n\nL\u00e4s mer\n\n### Matchrapport: Arlanda-SFK Herr (2025-05-20)\n\nL\u00e4s mer\n\n### Matchrapport: Brage-SFK Dam (2025-05-13)\n\nL\u00e4s mer\n\n### Matchrapport: FC Stockholm-SFK Herr (2025-05-13)\n\nL\u00e4s mer\n\n### Matchrapport: \u00d6sterv\u00e5la-SFK Dam (2025-05-10)\n\nL\u00e4s mer\n\n### Matchrapport: Eskilstuna-SFK Herr (2025-05-05)\n\nL\u00e4s mer\n\n### Matchrapport: SFK Dam-Karlberg (2025-05-05)\n\nL\u00e4s mer\n\n### Matchrapporter fr\u00e5n herr och dam (2025-04-30)\n\nL\u00e4s mer\n\n### Matchrapport: SFK Herr-Team TG (2025-04-22)\n\nL\u00e4s mer\n\n### Matchrapport: Bergn\u00e4set-SFK Dam (2025-04-20)\n\nL\u00e4s mer\n\n### Matchrapport: Damernas hemmapremi\u00e4r (2025-04-15)\n\nL\u00e4s mer\n\n### Matchrapport: ESK-SFK, Ettan Norra (2025-04-14)\n\nL\u00e4s mer\n\n### Inf\u00f6r damernas hemmapremi\u00e4r (2025-04-10)\n\nL\u00e4s mer\n\n### Damerna vann \u00f6vertygande i premi\u00e4ren (2025-04-08)\n\nL\u00e4s mer\n\n### F\u00f6rlust f\u00f6r herrarna i hemmapremi\u00e4ren (2025-04-05)\n\nL\u00e4s mer\n\n### Inf\u00f6r damernas seriepremi\u00e4r (2025-04-03)\n\nL\u00e4s mer\n\n### Fo\u0308rlust i seriepremia\u0308ren fo\u0308r herrarna (2025-03-31)\n\nL\u00e4s mer\n\n### Inf\u00f6r Nordic United FC\u2013Sollentuna FK (2025-03-28)\n\nL\u00e4s mer\n\n### \u00c5rets s\u00e4songskort \u00e4r h\u00e4r! (2025-03-27)\n\nL\u00e4s mer\n\n### Utbildningar i fokus (2025-03-26)\n\nL\u00e4s mer\n\n### Marcus Burman skriver p\u00e5 f\u00f6r SFK (2025-02-26)\n\nL\u00e4s mer\n\n### Tv\u00e5 nya FU ska st\u00f6tta barn- och ungdomslagen (2025-02-26)\n\nL\u00e4s mer\n\n### Fr\u00e5n ungdom till elit \u2013 hur skapar vi en utvecklande milj\u00f6? En f\u00f6rel\u00e4sning med Johan Fallby. (2025-02-02)\n\nL\u00e4s mer\n\n### Georgios ska f\u00e5 flickakademin att ta n\u00e4sta kliv (2025-02-17)\n\nL\u00e4s mer\n\n### Infometric och SFK f\u00f6rdjupar sitt samarbete (2025-02-11)\n\nL\u00e4s mer\n\n### L\u00e4r k\u00e4nna Nihmya \u2013 ny assisterande tr\u00e4nare f\u00f6r herr och huvudtr\u00e4nare P19 (2025-02-10)\n\nL\u00e4s mer\n\n### Damerna f\u00f6rbereder sig f\u00f6r s\u00e4songen 2025 (2025-02-10)\n\nL\u00e4s mer\n\n### \u00c5rsm\u00f6te \u2013 save the date (2025-01-01)\n\nL\u00e4s mer\n\n### Vill du eller n\u00e5gon du k\u00e4nner sitta i v\u00e5r styrelse? (2025-01-14)\n\nL\u00e4s mer\n\n### Ladingen blir partner till SFK (2025-01-09)\n\nL\u00e4s mer\n\n### SFK s\u00f6ker fler Fotbollsutvecklare (2025-01-09)\n\nL\u00e4s mer\n\n### Christopher Leal l\u00e4mnar SFK (2024-12-04)\n\nL\u00e4s mer\n\n### Aydin l\u00e4mnar SFK (2024-12-02)\n\nL\u00e4s mer\n\n### Stark s\u00e4song f\u00f6r v\u00e5r pojkakademi (2024-11-29)\n\nL\u00e4s mer\n\n### Heltidsanst\u00e4lld tr\u00e4nare till v\u00e5r flickakademi (2024-11-27)\n\nL\u00e4s mer\n\n### Vill du bli en del av v\u00e5r akademi? (2024-11-21)\n\nL\u00e4s mer\n\n### Ytterligare FU till barn- och ungdomsverksamheten (2024-09-24)\n\nL\u00e4s mer\n\n### SFK-\u00d6rebro i Svenska Cupen (2024-09-13)\n\nL\u00e4s mer\n\n### Nu drar vi ig\u00e5ng utvecklingspass (2024-08-15)\n\nL\u00e4s mer\n\n### Inf\u00f6r h\u00f6sten \u2013 herrlaget (2024-08-14)\n\nL\u00e4s mer\n\n### Wilgot Marshage klar f\u00f6r SFK (2024-08-03)\n\nL\u00e4s mer\n\n### Inf\u00f6r h\u00f6sten \u2013 damlaget (2024-08-02)\n\nL\u00e4s mer\n\n### Oscar Sj\u00f6strand klar f\u00f6r Sandviken (2024-07-29)\n\nL\u00e4s mer\n\n### Kevin rekryteras till sportsliga verksamheten (2024-07-24)\n\nL\u00e4s mer\n\n## Kontakt\n\nSollentuna Fotbollsklubb Ribbings v\u00e4g 50B (Edsbergs sportf\u00e4lt) 192 52 Sollentuna, info@sollentunafk.se",
  "html": "",
  "extracted_news": [
    {
      "date": "2025-05-20",
      "title": "Matchrapport: Arlanda-SFK Herr",
      "content": "L\u00e4s mer",
      "first_seen": "2025-05-22T15:35:17.908834",
      "url": "https://www.sollentunafk.se/aktuellt/"
    },
    {
      "date": "2025-05-20",
      "title": "Matchrapport: SFK Dam-T\u00e4by",
      "content": "L\u00e4s mer",
      "first_seen": "2025-05-22T15:35:17.908836",
      "url": "https://www.sollentunafk.se/aktuellt/"
    },
    {
      "date": "2025-05-13",
      "title": "Matchrapport: Brage-SFK Dam",
      "content": "L\u00e4s mer",
      "first_seen": "2025-05-22T15:35:17.908837",
      "url": "https://www.sollentunafk.se/aktuellt/"
    },
    {
      "date": "2025-05-13",
      "title": "Matchrapport: FC Stockholm-SFK Herr",
      "content": "L\u00e4s mer",
      "first_seen": "2025-05-22T15:35:17.908838",
      "url": "https://www.sollentunafk.se/aktuellt/"
    },
    {
      "date": "2025-05-10",
      "title": "Matchrapport: \u00d6sterv\u00e5la-SFK Dam",
      "content": "L\u00e4s mer",
      "first_seen": "2025-05-22T15:35:17.908839",
      "url": "https://www.sollentunafk.se/aktuellt/"
    },
    {
      "date": "2025-05-05",
      "title": "Matchrapport: Eskilstuna-SFK Herr",
      "content": "L\u00e4s mer",
      "first_seen": "2025-05-22T15:35:17.908840",
      "url": "https://www.sollentunafk.se/aktuellt/"
    },
    {
      "date": "2025-05-05",
      "title": "Matchrapport: SFK Dam-Karlberg",
      "content": "L\u00e4s mer",
      "first_seen": "2025-05-22T15:35:17.908841",
      "url": "https://www.sollentunafk.se/aktuellt/"
    },
    {
      "date": "2025-04-30",
      "title": "Matchrapporter fr\u00e5n herr och dam",
      "content": "L\u00e4s mer",
      "first_seen": "2025-05-22T15:35:17.908842",
      "url": "https://www.sollentunafk.se/aktuellt/"
    },
    {
      "date": "2025-04-22",
      "title": "Matchrapport: SFK Herr-Team TG",
      "content": "L\u00e4s mer",
      "first_seen": "2025-05-22T15:35:17.908843",
      "url": "https://www.sollentunafk.se/aktuellt/"
    },
    {
      "date": "2025-04-20",
      "title": "Matchrapport: Bergn\u00e4set-SFK Dam",
      "content": "L\u00e4s mer",
      "first_seen": "2025-05-22T15:35:17.908844",
      "url": "https://www.sollentunafk.se/aktuellt/"
    },
    {
      "date": "2025-04-15",
      "title": "Matchrapport: Damernas hemmapremi\u00e4r",
      "content": "L\u00e4s mer",
      "first_seen": "2025-05-22T15:35:17.908846",
      "url": "https://www.sollentunafk.se/aktuellt/"
    },
    {
      "date": "2025-04-14",
      "title": "Matchrapport: ESK-SFK, Ettan Norra",
      "content": "L\u00e4s mer",
      "first_seen": "2025-05-22T15:35:17.908847",
      "url": "https://www.sollentunafk.se/aktuellt/"
    },
    {
      "date": "2025-04-10",
      "title": "Inf\u00f6r damernas hemmapremi\u00e4r",
      "content": "L\u00e4s mer",
      "first_seen": "2025-05-22T15:35:17.908848",
      "url": "https://www.sollentunafk.se/aktuellt/"
    },
    {
      "date": "2025-04-08",
      "title": "Damerna vann \u00f6vertygande i premi\u00e4ren",
      "content": "L\u00e4s mer",
      "first_seen": "2025-05-22T15:35:17.908849",
      "url": "https://www.sollentunafk.se/aktuellt/"
    },
    {
      "date": "2025-04-05",
      "title": "F\u00f6rlust f\u00f6r herrarna i hemmapremi\u00e4ren",
      "content": "L\u00e4s mer",
      "first_seen": "2025-05-22T15:35:17.908850",
      "url": "https://www.sollentunafk.se/aktuellt/"
    },
    {
      "date": "2025-04-03",
      "title": "Inf\u00f6r damernas seriepremi\u00e4r",
      "content": "L\u00e4s mer",
      "first_seen": "2025-05-22T15:35:17.908851",
      "url": "https://www.sollentunafk.se/aktuellt/"
    },
    {
      "date": "2025-03-31",
      "title": "Fo\u0308rlust i seriepremia\u0308ren fo\u0308r herrarna",
      "content": "L\u00e4s mer",
      "first_seen": "2025-05-22T15:35:17.908852",
      "url": "https://www.sollentunafk.se/aktuellt/"
    },
    {
      "date": "2025-03-28",
      "title": "Inf\u00f6r Nordic United FC\u2013Sollentuna FK",
      "content": "L\u00e4s mer",
      "first_seen": "2025-05-22T15:35:17.908853",
      "url": "https://www.sollentunafk.se/aktuellt/"
    },
    {
      "date": "2025-03-27",
      "title": "\u00c5rets s\u00e4songskort \u00e4r h\u00e4r!",
      "content": "L\u00e4s mer",
      "first_seen": "2025-05-22T15:35:17.908854",
      "url": "https://www.sollentunafk.se/aktuellt/"
    },
    {
      "date": "2025-03-26",
      "title": "Utbildningar i fokus",
      "content": "L\u00e4s mer",
      "first_seen": "2025-05-22T15:35:17.908855",
      "url": "https://www.sollentunafk.se/aktuellt/"
    },
    {
      "date": "2025-03-10",
      "title": "Marcus Burman skriver p\u00e5 f\u00f6r SFK",
      "content": "L\u00e4s mer",
      "first_seen": "2025-05-22T15:35:17.908856",
      "url": "https://www.sollentunafk.se/aktuellt/"
    },
    {
      "date": "2025-03-10",
      "title": "Tv\u00e5 nya FU ska st\u00f6tta barn- och ungdomslagen",
      "content": "L\u00e4s mer",
      "first_seen": "2025-05-22T15:35:17.908857",
      "url": "https://www.sollentunafk.se/aktuellt/"
    },
    {
      "date": "2025-03-02",
      "title": "Fr\u00e5n ungdom till elit \u2013 hur skapar vi en utvecklande milj\u00f6? En f\u00f6rel\u00e4sning med Johan Fallby.",
      "content": "L\u00e4s mer",
      "first_seen": "2025-05-22T15:35:17.908858",
      "url": "https://www.sollentunafk.se/aktuellt/"
    },
    {
      "date": "2025-02-26",
      "title": "Georgios ska f\u00e5 flickakademin att ta n\u00e4sta kliv",
      "content": "L\u00e4s mer",
      "first_seen": "2025-05-22T15:35:17.908859",
      "url": "https://www.sollentunafk.se/aktuellt/"
    },
    {
      "date": "2025-02-17",
      "title": "Infometric och SFK f\u00f6rdjupar sitt samarbete",
      "content": "L\u00e4s mer",
      "first_seen": "2025-05-22T15:35:17.908860",
      "url": "https://www.sollentunafk.se/aktuellt/"
    },
    {
      "date": "2025-02-11",
      "title": "L\u00e4r k\u00e4nna Nihmya \u2013 ny assisterande tr\u00e4nare f\u00f6r herr och huvudtr\u00e4nare P19",
      "content": "L\u00e4s mer",
      "first_seen": "2025-05-22T15:35:17.908861",
      "url": "https://www.sollentunafk.se/aktuellt/"
    },
    {
      "date": "2025-02-10",
      "title": "Damerna f\u00f6rbereder sig f\u00f6r s\u00e4songen 2025",
      "content": "L\u00e4s mer",
      "first_seen": "2025-05-22T15:35:17.908863",
      "url": "https://www.sollentunafk.se/aktuellt/"
    },
    {
      "date": "2025-02-01",
      "title": "\u00c5rsm\u00f6te \u2013 save the date",
      "content": "L\u00e4s mer",
      "first_seen": "2025-05-22T15:35:17.908864",
      "url": "https://www.sollentunafk.se/aktuellt/"
    },
    {
      "date": "2025-01-14",
      "title": "Vill du eller n\u00e5gon du k\u00e4nner sitta i v\u00e5r styrelse?",
      "content": "L\u00e4s mer",
      "first_seen": "2025-05-22T15:35:17.908865",
      "url": "https://www.sollentunafk.se/aktuellt/"
    },
    {
      "date": "2025-01-09",
      "title": "Ladingen blir partner till SFK",
      "content": "L\u00e4s mer",
      "first_seen": "2025-05-22T15:35:17.908866",
      "url": "https://www.sollentunafk.se/aktuellt/"
    },
    {
      "date": "2025-01-09",
      "title": "SFK s\u00f6ker fler Fotbollsutvecklare",
      "content": "L\u00e4s mer",
      "first_seen": "2025-05-22T15:35:17.908867",
      "url": "https://www.sollentunafk.se/aktuellt/"
    },
    {
      "date": "2024-12-04",
      "title": "Christopher Leal l\u00e4mnar SFK",
      "content": "L\u00e4s mer",
      "first_seen": "2025-05-22T15:35:17.908868",
      "url": "https://www.sollentunafk.se/aktuellt/"
    },
    {
      "date": "2024-12-02",
      "title": "Aydin l\u00e4mnar SFK",
      "content": "L\u00e4s mer",
      "first_seen": "2025-05-22T15:35:17.908869",
      "url": "https://www.sollentunafk.se/aktuellt/"
    },
    {
      "date": "2024-11-29",
      "title": "Stark s\u00e4song f\u00f6r v\u00e5r pojkakademi",
      "content": "L\u00e4s mer",
      "first_seen": "2025-05-22T15:35:17.908870",
      "url": "https://www.sollentunafk.se/aktuellt/"
    },
    {
      "date": "2024-11-27",
      "title": "Heltidsanst\u00e4lld tr\u00e4nare till v\u00e5r flickakademi",
      "content": "L\u00e4s mer",
      "first_seen": "2025-05-22T15:35:17.908871",
      "url": "https://www.sollentunafk.se/aktuellt/"
    },
    {
      "date": "2024-11-21",
      "title": "Vill du bli en del av v\u00e5r akademi?",
      "content": "L\u00e4s mer",
      "first_seen": "2025-05-22T15:35:17.908872",
      "url": "https://www.sollentunafk.se/aktuellt/"
    },
    {
      "date": "2024-09-24",
      "title": "Ytterligare FU till barn- och ungdomsverksamheten",
      "content": "L\u00e4s mer",
      "first_seen": "2025-05-22T15:35:17.908873",
      "url": "https://www.sollentunafk.se/aktuellt/"
    },
    {
      "date": "2024-09-13",
      "title": "SFK-\u00d6rebro i Svenska Cupen",
      "content": "L\u00e4s mer",
      "first_seen": "2025-05-22T15:35:17.908874",
      "url": "https://www.sollentunafk.se/aktuellt/"
    },
    {
      "date": "2024-08-15",
      "title": "Nu drar vi ig\u00e5ng utvecklingspass",
      "content": "L\u00e4s mer",
      "first_seen": "2025-05-22T15:35:17.908875",
      "url": "https://www.sollentunafk.se/aktuellt/"
    },
    {
      "date": "2024-08-14",
      "title": "Inf\u00f6r h\u00f6sten \u2013 herrlaget",
      "content": "L\u00e4s mer",
      "first_seen": "2025-05-22T15:35:17.908876",
      "url": "https://www.sollentunafk.se/aktuellt/"
    },
    {
      "date": "2024-08-03",
      "title": "Wilgot Marshage klar f\u00f6r SFK",
      "content": "L\u00e4s mer",
      "first_seen": "2025-05-22T15:35:17.908877",
      "url": "https://www.sollentunafk.se/aktuellt/"
    },
    {
      "date": "2024-08-02",
      "title": "Inf\u00f6r h\u00f6sten \u2013 damlaget",
      "content": "L\u00e4s mer",
      "first_seen": "2025-05-22T15:35:17.908878",
      "url": "https://www.sollentunafk.se/aktuellt/"
    },
    {
      "date": "2024-07-29",
      "title": "Oscar Sj\u00f6strand klar f\u00f6r Sandviken",
      "content": "L\u00e4s mer",
      "first_seen": "2025-05-22T15:35:17.908879",
      "url": "https://www.sollentunafk.se/aktuellt/"
    },
    {
      "date": "2024-07-24",
      "title": "Kevin rekryteras till sportsliga verksamheten",
      "content": "L\u00e4s mer",
      "first_seen": "2025-05-22T15:35:17.908880",
      "url": "https://www.sollentunafk.se/aktuellt/"
    },
    {
      "date": "2025-05-28",
      "title": "Matchrapport: Heffnersklubban-SFK Dam",
      "content": "L\u00e4s mer",
      "first_seen": "2025-05-28T14:00:29.370889",
      "url": "https://www.sollentunafk.se/aktuellt/"
    },
    {
      "date": "2025-05-28",
      "title": "Matchrapport: SFK Herr-Karlstad",
      "content": "L\u00e4s mer",
      "first_seen": "2025-05-28T14:00:29.370891",
      "url": "https://www.sollentunafk.se/aktuellt/"
    }
  ],
  "general_info": {
    "body": "Ettanfotboll.se drivs av f\u00f6reningen Ettanfotboll. F\u00f6reningen Ettanfotboll \u00e4r en intresseorganisation f\u00f6r de 32 klubbarna i Ettan. Uppdraget \u00e4r att driva utvecklingen av den semiprofessionella fotbollen; sportsligt, ekonomiskt, kommersiellt och administrativt.",
    "description": "Aktuellt \u2013 Sollentuna FK",
    "contact_info": "Sollentuna Fotbollsklubb Ribbings v\u00e4g 50B (Edsbergs sportf\u00e4lt) 192 52 Sollentuna, info@sollentunafk.se"
  },
  "timestamp": "2025-05-28T19:18:39.274834",
  "stored_at": "2025-05-28T19:18:39.284174"
}