{
  "url": "https://sollentunanorra.scout.se/nyheter/",
  "title": "https://sollentunanorra.scout.se/nyheter/",
  "content": "# https://sollentunanorra.scout.se/nyheter/\n\nNyheter - Sollentuna Norra Scoutk\u00e5r\n\nV\u00e4lkommen till Sollentuna Norra Scoutk\u00e5r, d\u00e4r vi erbjuder \u00e4ventyr och gemenskap f\u00f6r scouter.\n\n## Nyheter\n\n### V\u00e4lkommen till k\u00e5rhajken 2025 \u2013 Amerikaresan (2025-05-28)\n\nHej, Nu \u00e4r det snart dags f\u00f6r k\u00e5rhajk, det \u00e4r ett tillf\u00e4lle f\u00f6r alla scouter i Sollentuna Norra att vara ute p\u00e5 ett gemensamt \u00e4ventyr,\u2026\n\n### Bilder fr\u00e5n Uppt\u00e4ckarnas aprilhajk 2025 (2025-04-01)\n\nH\u00e4r kommer n\u00e5gra bilder fr\u00e5n Uppt\u00e4ckarnas aprilhajk (2025): Stort tack f\u00f6r en h\u00e4rlig hajk med era barn! De k\u00e4mpade p\u00e5 bra i b\u00e5de sol, hagel\u2026\n\n### Inbjudan till sommarens scoutl\u00e4ger 2025 (2025-05-01)\n\nHej, nu \u00e4r det dags att b\u00f6rja t\u00e4nka p\u00e5 sommarl\u00e4ger! Nytt f\u00f6r i \u00e5r \u00e4r att man kommer att ans\u00f6ka om en plats p\u00e5 l\u00e4gret\u2026.\n\n### Sommarens l\u00e4ger p\u00e5 Ora v3.0 (2025-06-01)\n\nSommarens l\u00e4ger p\u00e5 Ora v3.0 genomf\u00f6rs tillsammans med Sollentuna S\u00f6dra, Jakobsberg, M\u00e4rsta och Svartb\u00e4ckens scoutk\u00e5r och temat kommer att vara Vilda Western. H\u00e5ll utkik, ans\u00f6kan\u2026\n\n### K\u00e5rst\u00e4mma 2025 (2025-05-15)\n\nV\u00e4lkomna alla medlemmar i Sollentuna Norra Scoutk\u00e5r till v\u00e5rt eget \u00e5rsm\u00f6te. Under kv\u00e4llen pratar vi om det som gjorts i k\u00e5ren under 2024, och diskuterar\u2026\n\n### Terminsstart v\u00e5ren 2025 (2025-01-20)\n\nVecka 4 startar v\u00e5rterminen \u2013 Uppt\u00e4ckarna i avdelningen Skogen startar sin termin 20 januari 18:30-20 vid Kupan. H\u00e5ll koll p\u00e5 e-mailen \u2013 varje avdelning skickar\u2026\n\n### Terminsavslutning december 2024 (2024-12-20)\n\nD\u00e5 har Sollentuna Norra haft sin avslutning f\u00f6r 2024 p\u00e5 St:Larsg\u00e5rden i Norrviken. Det bj\u00f6ds enligt tradition p\u00e5 fackelt\u00e5g fr\u00e5n Norrvikens torg, fika, bevism\u00e4rkesutdelning och\u2026\n\n### Nu s\u00e4ljer vi julgranar f\u00f6r fullt! (2024-11-01)\n\nNu s\u00e4ljer vi julgranar f\u00f6r fullt! Fina svenska kvalitetsgranar fr\u00e5n Gunnars Granar. Vi st\u00e5r vid scoutstugan Kupan p\u00e5 Kistav\u00e4gen 11 varje dag fram till den\u2026\n\n### Inbjudan till Sollentuna Norras Terminsavslutning h\u00f6sten 2024 (2024-10-15)\n\nSom en p\u00e5minnelse s\u00e5 finns inbjudan till Sollentuna Norras Terminsavslutning h\u00f6sten 2024 i v\u00e5r kalender. Du hittar den h\u00e4r.\n\n### Julgransf\u00f6rs\u00e4ljning 2024 \u2013 Anm\u00e4lan \u00f6ppen (2024-11-29)\n\nDen 29 november kommer en lastbil med \u00f6ver 700 julgranar till scoutstugan Kupan, och vi beh\u00f6ver er hj\u00e4lp att s\u00e4lja dem! Scoutk\u00e5ren s\u00e4ljer granar vid\u2026\n\n### Patrullen Yxan vann Silverboken 2024 (2024-09-01)\n\nUnder den traditionsenliga t\u00e4vlingen Silverboken/Mickeljakten/Kurreskuttet/Silversvansen mellan alla scoutk\u00e5rer i Sollentuna vann i \u00e5r, f\u00f6r f\u00f6rsta g\u00e5ngen p\u00e5 \u00f6ver 20 \u00e5r, Sollentuna Norras \u00e4ventyrarpatrullen Yxan sj\u00e4lva\u2026\n\n### H\u00f6stterminen 2024 ig\u00e5ng (2024-08-20)\n\nNu \u00e4r h\u00f6stterminen 2024 ig\u00e5ng! Terminsprogram skickas ut via mail och delas ut som papper till alla scouter men kommer s\u00e5 sm\u00e5ningom \u00e4ven l\u00e4ggas upp\u2026",
  "html": "",
  "extracted_news": [
    {
      "date": "2025-05-22",
      "title": "V\u00e4lkommen till k\u00e5rhajken 2025 \u2013 Amerikaresan",
      "content": "Hej, Nu \u00e4r det snart dags f\u00f6r k\u00e5rhajk, det \u00e4r ett tillf\u00e4lle f\u00f6r alla scouter i Sollentuna Norra att vara ute p\u00e5 ett gemensamt \u00e4ventyr,\u2026",
      "first_seen": "2025-05-22T15:44:23.548982",
      "url": "https://sollentunanorra.scout.se/nyheter/"
    },
    {
      "date": "2025-04-01",
      "title": "Bilder fr\u00e5n Uppt\u00e4ckarnas aprilhajk 2025",
      "content": "H\u00e4r kommer n\u00e5gra bilder fr\u00e5n Uppt\u00e4ckarnas aprilhajk (2025): Stort tack f\u00f6r en h\u00e4rlig hajk med era barn! De k\u00e4mpade p\u00e5 bra i b\u00e5de sol, hagel\u2026",
      "first_seen": "2025-05-22T15:44:23.548985",
      "url": "https://sollentunanorra.scout.se/nyheter/"
    },
    {
      "date": "2025-05-01",
      "title": "Inbjudan till sommarens scoutl\u00e4ger 2025",
      "content": "Hej, nu \u00e4r det dags att b\u00f6rja t\u00e4nka p\u00e5 sommarl\u00e4ger! Nytt f\u00f6r i \u00e5r \u00e4r att man kommer att ans\u00f6ka om en plats p\u00e5 l\u00e4gret\u2026.",
      "first_seen": "2025-05-22T15:44:23.548987",
      "url": "https://sollentunanorra.scout.se/nyheter/"
    },
    {
      "date": "2025-05-01",
      "title": "Sommarens l\u00e4ger p\u00e5 Ora v3.0",
      "content": "Sommarens l\u00e4ger p\u00e5 Ora v3.0 genomf\u00f6rs tillsammans med Sollentuna S\u00f6dra, Jakobsberg, M\u00e4rsta och Svartb\u00e4ckens scoutk\u00e5r och temat kommer att vara Vilda Western. H\u00e5ll utkik, ans\u00f6kan\u2026",
      "first_seen": "2025-05-22T15:44:23.548989",
      "url": "https://sollentunanorra.scout.se/nyheter/"
    },
    {
      "date": "2025-05-01",
      "title": "K\u00e5rst\u00e4mma 2025",
      "content": "V\u00e4lkomna alla medlemmar i Sollentuna Norra Scoutk\u00e5r till v\u00e5rt eget \u00e5rsm\u00f6te. Under kv\u00e4llen pratar vi om det som gjorts i k\u00e5ren under 2024, och diskuterar\u2026",
      "first_seen": "2025-05-22T15:44:23.548991",
      "url": "https://sollentunanorra.scout.se/nyheter/"
    },
    {
      "date": "2025-01-20",
      "title": "Terminsstart v\u00e5ren 2025",
      "content": "Vecka 4 startar v\u00e5rterminen \u2013 Uppt\u00e4ckarna i avdelningen Skogen startar sin termin 20 januari 18:30-20 vid Kupan. H\u00e5ll koll p\u00e5 e-mailen \u2013 varje avdelning skickar\u2026",
      "first_seen": "2025-05-22T15:44:23.548993",
      "url": "https://sollentunanorra.scout.se/nyheter/"
    },
    {
      "date": "2024-12-20",
      "title": "Terminsavslutning december 2024",
      "content": "D\u00e5 har Sollentuna Norra haft sin avslutning f\u00f6r 2024 p\u00e5 St:Larsg\u00e5rden i Norrviken. Det bj\u00f6ds enligt tradition p\u00e5 fackelt\u00e5g fr\u00e5n Norrvikens torg, fika, bevism\u00e4rkesutdelning och\u2026",
      "first_seen": "2025-05-22T15:44:23.548995",
      "url": "https://sollentunanorra.scout.se/nyheter/"
    },
    {
      "date": "2024-11-01",
      "title": "Nu s\u00e4ljer vi julgranar f\u00f6r fullt!",
      "content": "Nu s\u00e4ljer vi julgranar f\u00f6r fullt! Fina svenska kvalitetsgranar fr\u00e5n Gunnars Granar. Vi st\u00e5r vid scoutstugan Kupan p\u00e5 Kistav\u00e4gen 11 varje dag fram till den\u2026",
      "first_seen": "2025-05-22T15:44:23.548997",
      "url": "https://sollentunanorra.scout.se/nyheter/"
    },
    {
      "date": "2024-10-01",
      "title": "Inbjudan till Sollentuna Norras Terminsavslutning h\u00f6sten 2024",
      "content": "Som en p\u00e5minnelse s\u00e5 finns inbjudan till Sollentuna Norras Terminsavslutning h\u00f6sten 2024 i v\u00e5r kalender. Du hittar den h\u00e4r.",
      "first_seen": "2025-05-22T15:44:23.548999",
      "url": "https://sollentunanorra.scout.se/nyheter/"
    },
    {
      "date": "2024-11-29",
      "title": "Julgransf\u00f6rs\u00e4ljning 2024 \u2013 Anm\u00e4lan \u00f6ppen",
      "content": "Den 29 november kommer en lastbil med \u00f6ver 700 julgranar till scoutstugan Kupan, och vi beh\u00f6ver er hj\u00e4lp att s\u00e4lja dem! Scoutk\u00e5ren s\u00e4ljer granar vid\u2026",
      "first_seen": "2025-05-22T15:44:23.549001",
      "url": "https://sollentunanorra.scout.se/nyheter/"
    },
    {
      "date": "2024-10-01",
      "title": "Patrullen Yxan vann Silverboken 2024",
      "content": "Under den traditionsenliga t\u00e4vlingen Silverboken/Mickeljakten/Kurreskuttet/Silversvansen mellan alla scoutk\u00e5rer i Sollentuna vann i \u00e5r, f\u00f6r f\u00f6rsta g\u00e5ngen p\u00e5 \u00f6ver 20 \u00e5r, Sollentuna Norras \u00e4ventyrarpatrullen Yxan sj\u00e4lva\u2026",
      "first_seen": "2025-05-22T15:44:23.549003",
      "url": "https://sollentunanorra.scout.se/nyheter/"
    },
    {
      "date": "2024-09-01",
      "title": "H\u00f6stterminen 2024 ig\u00e5ng",
      "content": "Nu \u00e4r h\u00f6stterminen 2024 ig\u00e5ng! Terminsprogram skickas ut via mail och delas ut som papper till alla scouter men kommer s\u00e5 sm\u00e5ningom \u00e4ven l\u00e4ggas upp\u2026",
      "first_seen": "2025-05-22T15:44:23.549005",
      "url": "https://sollentunanorra.scout.se/nyheter/"
    }
  ],
  "general_info": {
    "body": "V\u00e4lkommen till Sollentuna Norra Scoutk\u00e5r, d\u00e4r vi erbjuder \u00e4ventyr och gemenskap f\u00f6r scouter.",
    "description": "Nyheter - Sollentuna Norra Scoutk\u00e5r",
    "contact_info": ""
  },
  "timestamp": "2025-05-28T19:29:27.477502",
  "stored_at": "2025-05-28T19:29:27.482873"
}